pagetree/__init__.py
pagetree/forms.py
pagetree/helpers.py
pagetree/models.py
pagetree/reports.py
pagetree/test_models.py
pagetree/urls.py
pagetree/views.py
pagetree/__pycache__/__init__.cpython-312.pyc
pagetree/__pycache__/forms.cpython-312.pyc
pagetree/__pycache__/helpers.cpython-312.pyc
pagetree/__pycache__/models.cpython-312.pyc
pagetree/__pycache__/reports.cpython-312.pyc
pagetree/__pycache__/test_models.cpython-312.pyc
pagetree/__pycache__/urls.cpython-312.pyc
pagetree/__pycache__/views.cpython-312.pyc
pagetree/generic/__init__.py
pagetree/generic/models.py
pagetree/generic/views.py
pagetree/generic/__pycache__/__init__.cpython-312.pyc
pagetree/generic/__pycache__/models.cpython-312.pyc
pagetree/generic/__pycache__/views.cpython-312.pyc
pagetree/management/__init__.py
pagetree/management/__pycache__/__init__.cpython-312.pyc
pagetree/management/commands/__init__.py
pagetree/management/commands/pull_from_prod.py
pagetree/management/commands/__pycache__/__init__.cpython-312.pyc
pagetree/migrations/0001_initial.py
pagetree/migrations/0002_delete_testblock.py
pagetree/migrations/__init__.py
pagetree/migrations/__pycache__/0001_initial.cpython-312.pyc
pagetree/migrations/__pycache__/0002_delete_testblock.cpython-312.pyc
pagetree/migrations/__pycache__/__init__.cpython-312.pyc
pagetree/static/pagetree/css/jquery-ui.min.css
pagetree/static/pagetree/css/loading.css
pagetree/static/pagetree/css/images/ui-icons_444444_256x240.png
pagetree/static/pagetree/css/images/ui-icons_555555_256x240.png
pagetree/static/pagetree/css/images/ui-icons_777620_256x240.png
pagetree/static/pagetree/css/images/ui-icons_777777_256x240.png
pagetree/static/pagetree/css/images/ui-icons_cc0000_256x240.png
pagetree/static/pagetree/css/images/ui-icons_ffffff_256x240.png
pagetree/static/pagetree/js/jquery-ui.min.js
pagetree/static/pagetree/js/jquery.cookie.js
pagetree/static/pagetree/js/src/clone-loading.js
pagetree/static/pagetree/js/src/pagetree-admin.js
pagetree/templates/__init__.py
django_pagetree-1.5.0.dist-info/LICENSE
django_pagetree-1.5.0.dist-info/METADATA
django_pagetree-1.5.0.dist-info/WHEEL
django_pagetree-1.5.0.dist-info/top_level.txt
django_pagetree-1.5.0.dist-info/RECORD
